min_number_lib/__init__.py
min_number_lib/__main__.py
min_number_lib/core.py
minnumberlib-0.1.0.dist-info/licenses/LICENSE
minnumberlib-0.1.0.dist-info/METADATA
minnumberlib-0.1.0.dist-info/WHEEL
minnumberlib-0.1.0.dist-info/entry_points.txt
minnumberlib-0.1.0.dist-info/top_level.txt
minnumberlib-0.1.0.dist-info/RECORD
