Metadata-Version: 2.4
Name: MinNumberLib
Version: 0.1.0
Summary: Find the smallest number from a list
Author: Mohammed Abdo Aljamal
Author-email: Mohammed Abdo Aljamal <aljmal7722@gmail.com>
License: 
Requires-Python: >=3.7
License-File: LICENSE
Dynamic: author
Dynamic: license-file
Dynamic: requires-python
